{
  "$schema": "./node_modules/@stryker-mutator/core/schema/stryker-schema.json",
  "testRunner": "vitest",
  "vitest": {
    "configFile": "vitest.config.ts"
  },
  "checkers": ["typescript"],
  "tsconfigFile": "packages/api/tsconfig.json",
  "mutate": [
    "packages/api/src/agent/**/*.ts",
    "packages/api/src/practices/**/*.ts",
    "!packages/api/src/**/*.test.ts",
    "!packages/api/src/test-helpers.ts"
  ],
  "coverageAnalysis": "perTest",
  "reporters": ["html", "clear-text", "progress"],
  "incremental": true,
  "htmlReporter": {
    "fileName": "reports/mutation/index.html"
  },
  "thresholds": {
    "high": 80,
    "low": 60,
    "break": null
  }
}
